setup.py
EasyPage.egg-info/PKG-INFO
EasyPage.egg-info/SOURCES.txt
EasyPage.egg-info/dependency_links.txt
EasyPage.egg-info/requires.txt
EasyPage.egg-info/top_level.txt
easypage/__init__.py
easypage/cdp.py
easypage/conn.py
easypage/definition.py
easypage/errors.py
easypage/event_manager.py
easypage/listener.py
easypage/logger.py
easypage/main.py
easypage/operate.py
easypage/options.py
easypage/request.py
easypage/response.py
easypage/settings.py
easypage/cdp_method/__init__.py
easypage/cdp_method/browser.py
easypage/cdp_method/css.py
easypage/cdp_method/dom.py
easypage/cdp_method/emulation.py
easypage/cdp_method/fetch.py
easypage/cdp_method/input.py
easypage/cdp_method/network.py
easypage/cdp_method/page.py
easypage/cdp_method/runtime.py
easypage/cdp_method/security.py
easypage/cdp_method/storage.py
easypage/cdp_method/target.py
easypage/driver/__init__.py
easypage/driver/browser.py
easypage/driver/driver.py
easypage/driver/page.py
easypage/utils/__init__.py
easypage/utils/browser_utils.py
easypage/utils/other_utils.py
easypage_async/__init__.py
easypage_async/conn.py