Metadata-Version: 1.0
Name: EasyPage
Version: 0.0.16
Summary: 基于 CDP 协议，简洁快速的浏览器控制 API
Home-page: UNKNOWN
Author: leviathangk
Author-email: 1015295213@qq.com
License: UNKNOWN
Keywords: EasyPage,page,browser
Platform: UNKNOWN
